{
  "name": "Flip.gg Lootbox $2.50",
  "description": "Optimized for flip.gg with cost $2.50",
  "cost": 2.5,
  "items": [
    {
      "name": "Small Coins",
      "value": 0.2,
      "rarity": "common",
      "probability": 0.5,
      "description": "Basic coins with minimal value"
    },
    {
      "name": "Token Bundle",
      "value": 0.625,
      "rarity": "uncommon",
      "probability": 0.25,
      "description": "Decent token bundle"
    },
    {
      "name": "Premium Item",
      "value": 2.0,
      "rarity": "rare",
      "probability": 0.15,
      "description": "Premium item worth most of box cost"
    },
    {
      "name": "Valuable Prize",
      "value": 7.5,
      "rarity": "epic",
      "probability": 0.08,
      "description": "High-value prize worth 3x the box"
    },
    {
      "name": "Mega Jackpot",
      "value": 25.0,
      "rarity": "legendary",
      "probability": 0.02,
      "description": "Massive jackpot - up to $1000!"
    }
  ]
}